pyrateye/__main__.py
RatEye/RatEye/bin/Release/netstandard2.0/RatEye.dll
RatEye/RatEye/bin/Release/netstandard2.0/x64/leptonica-1.82.0.dll
RatEye/RatEye/bin/Release/netstandard2.0/x64/tesseract50.dll
RatEye/RatEye/bin/Release/netstandard2.0/x86/leptonica-1.82.0.dll
RatEye/RatEye/bin/Release/netstandard2.0/x86/tesseract50.dll
pyrateye-0.0.1.dist-info/METADATA
pyrateye-0.0.1.dist-info/WHEEL
pyrateye-0.0.1.dist-info/RECORD
