Metadata-Version: 2.1
Name: pyrateye
Version: 0.0.1
Summary: RatEye ported to Python
Author: Martin Miglio
Author-email: marmig0404@gmail.com
Requires-Python: >=3.8,<3.12
Classifier: Programming Language :: Python :: 3
Classifier: Programming Language :: Python :: 3.8
Classifier: Programming Language :: Python :: 3.9
Classifier: Programming Language :: Python :: 3.10
Classifier: Programming Language :: Python :: 3.11
Requires-Dist: numpy (>=1.24.1,<2.0.0)
Requires-Dist: opencv-python (>=4.7.0.68,<5.0.0.0)
Requires-Dist: pythonnet (>=3.0.1,<4.0.0)
